py_syslab_app_sdk/__init__.py
py_syslab_app_sdk/connect_client.py
py_syslab_app_sdk/syslab_app_sdk.py
py_syslab_app_sdk/variable_info.py
syslabappsdk-0.1.2.dist-info/LICENSE
syslabappsdk-0.1.2.dist-info/METADATA
syslabappsdk-0.1.2.dist-info/WHEEL
syslabappsdk-0.1.2.dist-info/top_level.txt
syslabappsdk-0.1.2.dist-info/RECORD
