Metadata-Version: 2.1
Name: syslabappsdk
Version: 0.1.2
Summary: SDK for data interaction and function calls between Python APP and Syslab platform
Author-email: Suzhou-tongyuan <support@tongyuan.cc>
License: The MIT License (MIT)
Keywords: syslab,syslabappsdk,syslabapp,tongyuan
Classifier: Development Status :: 4 - Beta
Classifier: Intended Audience :: Developers
Classifier: Topic :: Software Development
Classifier: License :: OSI Approved :: MIT License
Classifier: Programming Language :: Python :: 3
Classifier: Programming Language :: Python :: 3.7
Classifier: Programming Language :: Python :: 3.8
Classifier: Programming Language :: Python :: 3.9
Classifier: Programming Language :: Python :: 3.10
Classifier: Programming Language :: Python :: 3.11
Requires-Python: <4,>=3.7
License-File: LICENSE
